trading_lib/__init__.py
trading_lib/backtest.py
trading_lib/db_manager.py
trading_lib/db_models.py
trading_lib/enums.py
trading_lib/strategy.py
trading_lib/typing.py
trading_lib/utils.py
trading_lib/core/typing.py
trading_lib/exchanges/__init__.py
trading_lib/exchanges/backtest_futures_exchange.py
trading_lib/exchanges/exchange.py
trading_lib/exchanges/futures_exchange.py
trading_lib/exchanges/mt5_futures_exchange.py
trading_lib/ict/__init__.py
trading_lib/ict/fvg.py
trading_lib/ict/mss.py
trading_lib/order_managers/__init__.py
trading_lib/order_managers/backtest_futures_order_manager.py
trading_lib/order_managers/futures_order_manager.py
trading_lib/order_managers/mt5_futures_order_manager.py
zjt_trading_lib-0.1.0.dist-info/METADATA
zjt_trading_lib-0.1.0.dist-info/WHEEL
zjt_trading_lib-0.1.0.dist-info/top_level.txt
zjt_trading_lib-0.1.0.dist-info/RECORD
